CHANGES.txt
MANIFEST.in
README.txt
setup.py
cs/__init__.py
cs.board.egg-info/PKG-INFO
cs.board.egg-info/SOURCES.txt
cs.board.egg-info/dependency_links.txt
cs.board.egg-info/entry_points.txt
cs.board.egg-info/namespace_packages.txt
cs.board.egg-info/not-zip-safe
cs.board.egg-info/paster_plugins.txt
cs.board.egg-info/requires.txt
cs.board.egg-info/top_level.txt
cs/board/__init__.py
cs/board/config.py
cs/board/configure.zcml
cs/board/rebuild_i18n.sh
cs/board/setuphandlers.py
cs/board/tests.py
cs/board/browser/__init__.py
cs/board/browser/api.py
cs/board/browser/boardview.pt
cs/board/browser/boardview.py
cs/board/browser/configure.zcml
cs/board/browser/documentview.pt
cs/board/browser/documentview.py
cs/board/content/__init__.py
cs/board/content/board.py
cs/board/content/boarddocument.py
cs/board/content/configure.zcml
cs/board/interfaces/__init__.py
cs/board/interfaces/board.py
cs/board/interfaces/boarddocument.py
cs/board/locales/cs.board-manual.pot
cs/board/locales/cs.board.pot
cs/board/locales/en/LC_MESSAGES/README.txt
cs/board/locales/en/LC_MESSAGES/cs.board.po
cs/board/locales/es/LC_MESSAGES/README.txt
cs/board/locales/es/LC_MESSAGES/cs.board.po
cs/board/locales/eu/LC_MESSAGES/README.txt
cs/board/locales/eu/LC_MESSAGES/cs.board.po
cs/board/portlets/__init__.py
cs/board/portlets/configure.zcml
cs/board/profiles/default/catalog.xml
cs/board/profiles/default/cs.board_various.txt
cs/board/profiles/default/factorytool.xml
cs/board/profiles/default/import_steps.xml
cs/board/profiles/default/metadata.xml
cs/board/profiles/default/portlets.xml
cs/board/profiles/default/rolemap.xml
cs/board/profiles/default/types.xml
cs/board/profiles/default/workflows.xml
cs/board/profiles/default/types/Board.xml
cs/board/profiles/default/types/BoardDocument.xml
cs/board/profiles/default/workflows/two_state_simple_workflow/definition.xml
cs/board/subscribers/__init__.py
cs/board/subscribers/boarddocument.py
cs/board/subscribers/configure.zcml
cs/board/subscribers/file.py
cs/board/tests/__init__.py
cs/board/tests/base.py
cs/board/tests/test_doctest.py
docs/HISTORY.txt
docs/INSTALL.txt
docs/LICENSE.GPL
docs/LICENSE.txt