Metadata-Version: 1.1
Name: cs.board
Version: 1.7.2
Summary: A simple board to publish official documents in Plone Sites
Home-page: http://svn.plone.org/svn/collective/
Author: Mikel Larreategi
Author-email: mlarreategi@codesyntax.com
License: GPL
Platform: UNKNOWN
Classifier: Framework :: Plone
Classifier: Intended Audience :: Developers
Classifier: License :: OSI Approved :: GNU General Public License (GPL)
